lyz/__init__.py
lyz-1.0.dist-info/METADATA
lyz-1.0.dist-info/WHEEL
lyz-1.0.dist-info/top_level.txt
lyz-1.0.dist-info/RECORD
